CODE_OF_CONDUCT.md
COPYING
COPYING.LESSER
anlearn/__init__.py
anlearn/_typing.py
anlearn/loda.py
anlearn/py.typed
anlearn/stats.py
anlearn/utils.py
anlearn-0.1.4.dist-info/COPYING.LESSER
anlearn-0.1.4.dist-info/COPYING
anlearn-0.1.4.dist-info/WHEEL
anlearn-0.1.4.dist-info/METADATA
anlearn-0.1.4.dist-info/RECORD
