Metadata-Version: 2.1
Name: anlearn
Version: 0.1.4
Summary: Anomaly learn - the anomaly detection package
Home-page: https://github.com/gaussalgo/anlearn
License: LGPL-3.0-or-later
Keywords: Anomaly detection,Outlier detection
Author: Ondrej Kurák
Author-email: kurak@gaussalgo.com
Requires-Python: >=3.6.10,<4.0.0
Classifier: Intended Audience :: Developers
Classifier: Intended Audience :: Education
Classifier: Intended Audience :: Science/Research
Classifier: License :: OSI Approved :: GNU Lesser General Public License v3 or later (LGPLv3+)
Classifier: Operating System :: OS Independent
Classifier: Programming Language :: Python :: 3
Classifier: Programming Language :: Python :: 3.7
Classifier: Programming Language :: Python :: 3.8
Classifier: Programming Language :: Python :: 3.9
Classifier: Topic :: Education
Classifier: Topic :: Scientific/Engineering
Classifier: Topic :: Software Development
Provides-Extra: docs
Requires-Dist: Pillow (>=8.1.0); extra == "docs"
Requires-Dist: Sphinx (>=3.4.3); extra == "docs"
Requires-Dist: matplotlib (>=3.3.4); extra == "docs"
Requires-Dist: numpy (>=1.19.0)
Requires-Dist: pandas (>=1.0.0); extra == "docs"
Requires-Dist: scikit-learn (>=0.23.0)
Requires-Dist: scipy (>=1.5.0)
Requires-Dist: sphinx-gallery (>=0.8.2); extra == "docs"
Requires-Dist: sphinx-rtd-theme (>=0.5.1); extra == "docs"
Requires-Dist: umap-learn (>=0.5.0); extra == "docs"
Project-URL: Documentation, https://anlearn.readthedocs.io/en/latest/
